bf_gen/__init__.py
bf_gen/preference.py
tests/__init__.py
tests/test_builder.py
bf_gen-0.1.1.dist-info/LICENSE
bf_gen-0.1.1.dist-info/METADATA
bf_gen-0.1.1.dist-info/WHEEL
bf_gen-0.1.1.dist-info/top_level.txt
bf_gen-0.1.1.dist-info/RECORD
