Metadata-Version: 2.1
Name: bf-gen
Version: 0.1.1
Summary: Supports you to generate Brainf**k code.
Home-page: https://github.com/capra314cabra/bf-gen
Author: capra314cabra
Author-email: capra314cabra@gmail.com
License: MIT
Keywords: brainfuck generator generate whitespace
Platform: UNKNOWN
Classifier: Programming Language :: Python :: 3
Classifier: License :: OSI Approved :: MIT License
Classifier: Operating System :: OS Independent
Requires-Python: >=3.6
